dbt_sync_server/__init__.py
dbt_sync_server/__main__.py
dbt_sync_server/dbt_rpc_client.py
dbt_sync_server/wsgi.py
dbt_sync_server-0.3.3.dist-info/entry_points.txt
dbt_sync_server-0.3.3.dist-info/WHEEL
dbt_sync_server-0.3.3.dist-info/METADATA
dbt_sync_server-0.3.3.dist-info/RECORD
