Metadata-Version: 2.1
Name: dbt-sync-server
Version: 0.3.3
Summary: Server which abstracts RPC and simplifies SQL execution and compilation
License: MIT
Author: Alex Butler
Requires-Python: >=3.8
Classifier: License :: OSI Approved :: MIT License
Classifier: Programming Language :: Python :: 3
Classifier: Programming Language :: Python :: 3.8
Classifier: Programming Language :: Python :: 3.9
Requires-Dist: Flask (>=1,<2)
Requires-Dist: Werkzeug (<2)
Requires-Dist: click (>=8.0.4,<9.0.0)
Requires-Dist: dbt-core (>1.0.1)
Requires-Dist: dbt-rpc (>=0.1.1,<0.2.0)
Requires-Dist: itsdangerous (==2.0.1)
